witch/__init__.py
witch/cli.py
witch/witch.py
witch-0.0.5.dist-info/DESCRIPTION.rst
witch-0.0.5.dist-info/METADATA
witch-0.0.5.dist-info/RECORD
witch-0.0.5.dist-info/WHEEL
witch-0.0.5.dist-info/entry_points.txt
witch-0.0.5.dist-info/metadata.json
witch-0.0.5.dist-info/top_level.txt
