Metadata-Version: 2.0
Name: witch
Version: 0.0.5
Summary: Platform independent which
Home-page: https://github.com/draperjames/witch
Author: James Draper
Author-email: james.draper@protonmail.com
License: MIT license
Keywords: witch
Platform: UNKNOWN
Classifier: Development Status :: 2 - Pre-Alpha
Classifier: Intended Audience :: Developers
Classifier: License :: OSI Approved :: MIT License
Classifier: Natural Language :: English
Classifier: Programming Language :: Python :: 2
Classifier: Programming Language :: Python :: 2.7
Classifier: Programming Language :: Python :: 3
Classifier: Programming Language :: Python :: 3.4
Classifier: Programming Language :: Python :: 3.5
Classifier: Programming Language :: Python :: 3.6
Requires-Dist: future
Requires-Dist: Click (>=6.0)
